steady_cell_phenotype/__init__.py
steady_cell_phenotype/_compute_cycles.py
steady_cell_phenotype/_compute_fixed_points.py
steady_cell_phenotype/_compute_trace.py
steady_cell_phenotype/_graph_layout.py
steady_cell_phenotype/_util.py
steady_cell_phenotype/bloom-filter.h
steady_cell_phenotype/complete-search-model-template.c
steady_cell_phenotype/cycle-table.h
steady_cell_phenotype/equation_system.py
steady_cell_phenotype/find_steady_states.m2-template
steady_cell_phenotype/gv-model-template.c
steady_cell_phenotype/length-count-array.h
steady_cell_phenotype/link-table.h
steady_cell_phenotype/mod3ops.h
steady_cell_phenotype/model-template.c
steady_cell_phenotype/poly.py
steady_cell_phenotype/scp_converter.py
steady_cell_phenotype/session_data_cache.py
steady_cell_phenotype/static/AdamKnapp.jpg
steady_cell_phenotype/static/GitHub-Mark-64px.png
steady_cell_phenotype/static/Iron_core.svg
steady_cell_phenotype/static/JuliaChifman.jpg
steady_cell_phenotype/static/LuisSV.png
steady_cell_phenotype/static/ReinhardLaubenbacher.jpg
steady_cell_phenotype/static/au-crest.svg
steady_cell_phenotype/static/axios.min.js
steady_cell_phenotype/static/axios.min.map
steady_cell_phenotype/static/continuity_selection.png
steady_cell_phenotype/static/d3-force.v2.min.js
steady_cell_phenotype/static/d3.v6.min.js
steady_cell_phenotype/static/fpn_oe.png
steady_cell_phenotype/static/fpn_oe_results.png
steady_cell_phenotype/static/icon.svg
steady_cell_phenotype/static/iron_core_state_space_cont.svg
steady_cell_phenotype/static/length_of_path.png
steady_cell_phenotype/static/logo.svg
steady_cell_phenotype/static/model_entry.png
steady_cell_phenotype/static/phased_envelope.png
steady_cell_phenotype/static/quickstart-1.png
steady_cell_phenotype/static/quickstart-2.png
steady_cell_phenotype/static/quickstart-3.png
steady_cell_phenotype/static/small_model.svg
steady_cell_phenotype/static/trace-state-config2.png
steady_cell_phenotype/static/trace-state-table.png
steady_cell_phenotype/static/w3.css
steady_cell_phenotype-0.3.5.dist-info/LICENSE
steady_cell_phenotype-0.3.5.dist-info/METADATA
steady_cell_phenotype-0.3.5.dist-info/WHEEL
steady_cell_phenotype-0.3.5.dist-info/top_level.txt
steady_cell_phenotype-0.3.5.dist-info/RECORD
