Metadata-Version: 2.1
Name: steady-cell-phenotype
Version: 0.3.5
Summary: A tool for the computation of steady states and exploration of dynamics in ternary intracellular biological networks.
Home-page: https://github.com/knappa/steadycellphenotype
Author: A. C. Knapp
Author-email: adam.knapp@medicine.ufl.edu
License: UNKNOWN
Project-URL: Bug Tracker, https://github.com/knappa/steadycellphenotype/issues
Platform: UNKNOWN
Classifier: Programming Language :: Python :: 3
Classifier: License :: OSI Approved :: MIT License
Classifier: Operating System :: OS Independent
Classifier: Development Status :: 4 - Beta
Classifier: Intended Audience :: Education
Classifier: Intended Audience :: Science/Research
Requires-Python: >=3.7
License-File: LICENSE
Requires-Dist: setuptools (>=54.0.0)
Requires-Dist: numpy (~=1.20.0)
Requires-Dist: numba (~=0.54.1)
Requires-Dist: attrs (~=21.2.0)
Requires-Dist: Flask (~=2.0.2)
Requires-Dist: matplotlib (~=3.4.1)
Requires-Dist: pathos (~=0.2.7)
Requires-Dist: networkx (>=2.5.1)
Requires-Dist: beautifulsoup4 (~=4.10.0)
Requires-Dist: lxml (~=4.6.4)
Requires-Dist: Werkzeug (~=2.0.2)
